{
  "slug": "econ_sunk_cost_FULL",
  "duration": 36.16,
  "cues": [
    {
      "start": 0.0,
      "end": 1.62,
      "text": "קנית כרטיס לסרט",
      "words": [
        {
          "t": "קנית",
          "s": 0.0,
          "e": 0.36
        },
        {
          "t": "כרטיס",
          "s": 0.36,
          "e": 0.76
        },
        {
          "t": "לסרט",
          "s": 0.76,
          "e": 1.62
        }
      ]
    },
    {
      "start": 1.62,
      "end": 2.94,
      "text": "איבדת אותו —",
      "words": [
        {
          "t": "איבדת",
          "s": 1.62,
          "e": 2.0
        },
        {
          "t": "אותו",
          "s": 2.0,
          "e": 2.94
        },
        {
          "t": "—",
          "s": 2.94,
          "e": 2.94
        }
      ]
    },
    {
      "start": 2.94,
      "end": 4.87,
      "text": "והשאלה היחידה שחשובה",
      "words": [
        {
          "t": "והשאלה",
          "s": 2.94,
          "e": 3.38
        },
        {
          "t": "היחידה",
          "s": 3.38,
          "e": 3.84
        },
        {
          "t": "שחשובה",
          "s": 3.84,
          "e": 4.44
        }
      ]
    },
    {
      "start": 4.87,
      "end": 5.7,
      "text": "היא לא כמה הוא עלה",
      "words": [
        {
          "t": "היא",
          "s": 4.87,
          "e": 5.37
        },
        {
          "t": "לא",
          "s": 5.37,
          "e": 5.53
        },
        {
          "t": "כמה",
          "s": 5.53,
          "e": 5.7
        },
        {
          "t": "הוא",
          "s": 5.7,
          "e": 5.7
        },
        {
          "t": "עלה",
          "s": 5.7,
          "e": 5.7
        }
      ]
    },
    {
      "start": 5.7,
      "end": 6.85,
      "text": "לך",
      "words": [
        {
          "t": "לך",
          "s": 5.7,
          "e": 6.85
        }
      ]
    },
    {
      "start": 6.85,
      "end": 9.58,
      "text": "זו עלות שקועה כסף ששילמת",
      "words": [
        {
          "t": "זו",
          "s": 6.85,
          "e": 7.03
        },
        {
          "t": "עלות",
          "s": 7.03,
          "e": 7.23
        },
        {
          "t": "שקועה",
          "s": 7.23,
          "e": 7.69
        },
        {
          "t": "כסף",
          "s": 8.31,
          "e": 8.57
        },
        {
          "t": "ששילמת",
          "s": 8.57,
          "e": 9.55
        }
      ]
    },
    {
      "start": 9.58,
      "end": 11.5,
      "text": "ואינך יכול להחזיר",
      "words": [
        {
          "t": "ואינך",
          "s": 9.58,
          "e": 9.8
        },
        {
          "t": "יכול",
          "s": 9.8,
          "e": 10.12
        },
        {
          "t": "להחזיר",
          "s": 10.12,
          "e": 11.5
        }
      ]
    },
    {
      "start": 11.5,
      "end": 13.1,
      "text": "האינטואיציה צועקת 'כבר",
      "words": [
        {
          "t": "האינטואיציה",
          "s": 11.5,
          "e": 12.02
        },
        {
          "t": "צועקת",
          "s": 12.02,
          "e": 13.0
        },
        {
          "t": "'כבר",
          "s": 13.0,
          "e": 13.1
        }
      ]
    },
    {
      "start": 13.1,
      "end": 15.96,
      "text": "שילמתי אסור לי לוותר' —",
      "words": [
        {
          "t": "שילמתי",
          "s": 13.1,
          "e": 14.1
        },
        {
          "t": "אסור",
          "s": 14.1,
          "e": 14.4
        },
        {
          "t": "לי",
          "s": 14.4,
          "e": 14.56
        },
        {
          "t": "לוותר'",
          "s": 14.56,
          "e": 14.84
        },
        {
          "t": "—",
          "s": 14.84,
          "e": 15.78
        }
      ]
    },
    {
      "start": 15.96,
      "end": 17.52,
      "text": "אבל מבחינה כלכלית זה",
      "words": [
        {
          "t": "אבל",
          "s": 15.96,
          "e": 16.14
        },
        {
          "t": "מבחינה",
          "s": 16.14,
          "e": 16.56
        },
        {
          "t": "כלכלית",
          "s": 16.56,
          "e": 17.4
        },
        {
          "t": "זה",
          "s": 17.4,
          "e": 17.52
        }
      ]
    },
    {
      "start": 17.52,
      "end": 19.34,
      "text": "לא רלוונטי בכלל",
      "words": [
        {
          "t": "לא",
          "s": 17.52,
          "e": 17.68
        },
        {
          "t": "רלוונטי",
          "s": 17.68,
          "e": 18.12
        },
        {
          "t": "בכלל",
          "s": 18.12,
          "e": 19.34
        }
      ]
    },
    {
      "start": 19.34,
      "end": 20.96,
      "text": "ההחלטה הנכונה נקבעת רק",
      "words": [
        {
          "t": "ההחלטה",
          "s": 19.34,
          "e": 19.77
        },
        {
          "t": "הנכונה",
          "s": 19.77,
          "e": 20.17
        },
        {
          "t": "נקבעת",
          "s": 20.17,
          "e": 20.7
        },
        {
          "t": "רק",
          "s": 20.7,
          "e": 20.89
        }
      ]
    },
    {
      "start": 20.96,
      "end": 21.6,
      "text": "על פי העלות",
      "words": [
        {
          "t": "על",
          "s": 20.96,
          "e": 21.12
        },
        {
          "t": "פי",
          "s": 21.12,
          "e": 21.24
        },
        {
          "t": "העלות",
          "s": 21.24,
          "e": 21.6
        }
      ]
    },
    {
      "start": 21.6,
      "end": 23.42,
      "text": "והתועלת העתידיות",
      "words": [
        {
          "t": "והתועלת",
          "s": 21.6,
          "e": 22.16
        },
        {
          "t": "העתידיות",
          "s": 22.16,
          "e": 23.42
        }
      ]
    },
    {
      "start": 23.42,
      "end": 24.72,
      "text": "האם הסרט שווה לך עכשיו",
      "words": [
        {
          "t": "האם",
          "s": 23.42,
          "e": 23.62
        },
        {
          "t": "הסרט",
          "s": 23.62,
          "e": 23.92
        },
        {
          "t": "שווה",
          "s": 23.92,
          "e": 24.18
        },
        {
          "t": "לך",
          "s": 24.18,
          "e": 24.38
        },
        {
          "t": "עכשיו",
          "s": 24.38,
          "e": 24.68
        }
      ]
    },
    {
      "start": 24.72,
      "end": 26.1,
      "text": "את מחיר הכרטיס החדש",
      "words": [
        {
          "t": "את",
          "s": 24.72,
          "e": 24.92
        },
        {
          "t": "מחיר",
          "s": 24.92,
          "e": 25.16
        },
        {
          "t": "הכרטיס",
          "s": 25.16,
          "e": 25.58
        },
        {
          "t": "החדש",
          "s": 25.58,
          "e": 26.1
        }
      ]
    },
    {
      "start": 26.1,
      "end": 29.08,
      "text": "מה שכבר הלך — הלך",
      "words": [
        {
          "t": "מה",
          "s": 26.1,
          "e": 26.94
        },
        {
          "t": "שכבר",
          "s": 26.94,
          "e": 27.28
        },
        {
          "t": "הלך",
          "s": 27.28,
          "e": 28.14
        },
        {
          "t": "—",
          "s": 28.14,
          "e": 28.14
        },
        {
          "t": "הלך",
          "s": 28.14,
          "e": 29.08
        }
      ]
    },
    {
      "start": 29.08,
      "end": 30.14,
      "text": "ואינו צריך להשפיע",
      "words": [
        {
          "t": "ואינו",
          "s": 29.08,
          "e": 29.28
        },
        {
          "t": "צריך",
          "s": 29.28,
          "e": 29.62
        },
        {
          "t": "להשפיע",
          "s": 29.62,
          "e": 30.06
        }
      ]
    },
    {
      "start": 30.14,
      "end": 30.84,
      "text": "על ההחלטה",
      "words": [
        {
          "t": "על",
          "s": 30.14,
          "e": 30.36
        },
        {
          "t": "ההחלטה",
          "s": 30.36,
          "e": 30.84
        }
      ]
    },
    {
      "start": 30.84,
      "end": 32.98,
      "text": "אם לקנות כרטיס חדש",
      "words": [
        {
          "t": "אם",
          "s": 30.84,
          "e": 30.98
        },
        {
          "t": "לקנות",
          "s": 30.98,
          "e": 31.26
        },
        {
          "t": "כרטיס",
          "s": 31.26,
          "e": 31.58
        },
        {
          "t": "חדש",
          "s": 31.58,
          "e": 32.98
        }
      ]
    },
    {
      "start": 32.98,
      "end": 34.67,
      "text": "עלות שקועה לא קובעת —",
      "words": [
        {
          "t": "עלות",
          "s": 32.98,
          "e": 33.2
        },
        {
          "t": "שקועה",
          "s": 33.2,
          "e": 33.58
        },
        {
          "t": "לא",
          "s": 33.58,
          "e": 33.74
        },
        {
          "t": "קובעת",
          "s": 33.74,
          "e": 34.67
        },
        {
          "t": "—",
          "s": 34.67,
          "e": 34.67
        }
      ]
    },
    {
      "start": 34.67,
      "end": 36.16,
      "text": "רק מה שעוד לפניך כן",
      "words": [
        {
          "t": "רק",
          "s": 34.67,
          "e": 34.87
        },
        {
          "t": "מה",
          "s": 34.87,
          "e": 35.05
        },
        {
          "t": "שעוד",
          "s": 35.05,
          "e": 35.27
        },
        {
          "t": "לפניך",
          "s": 35.27,
          "e": 35.71
        },
        {
          "t": "כן",
          "s": 35.71,
          "e": 36.13
        }
      ]
    }
  ]
}