{
  "slug": "ifrs9_equity_fvtpl_oci_election_FULL",
  "duration": 43.92,
  "cues": [
    {
      "start": 0.0,
      "end": 2.42,
      "text": "אתה מנסה להריץ מבחן SPPI",
      "words": [
        {
          "t": "אתה",
          "s": 0.0,
          "e": 0.22
        },
        {
          "t": "מנסה",
          "s": 0.22,
          "e": 0.6
        },
        {
          "t": "להריץ",
          "s": 0.6,
          "e": 0.94
        },
        {
          "t": "מבחן",
          "s": 0.94,
          "e": 1.84
        },
        {
          "t": "SPPI",
          "s": 1.84,
          "e": 2.42
        }
      ]
    },
    {
      "start": 2.42,
      "end": 4.32,
      "text": "על מניה ונתקע —",
      "words": [
        {
          "t": "על",
          "s": 2.42,
          "e": 2.78
        },
        {
          "t": "מניה",
          "s": 2.78,
          "e": 3.06
        },
        {
          "t": "ונתקע",
          "s": 3.06,
          "e": 3.8
        },
        {
          "t": "—",
          "s": 3.8,
          "e": 4.32
        }
      ]
    },
    {
      "start": 4.32,
      "end": 5.82,
      "text": "וזה בדיוק העניין",
      "words": [
        {
          "t": "וזה",
          "s": 4.32,
          "e": 4.52
        },
        {
          "t": "בדיוק",
          "s": 4.52,
          "e": 4.94
        },
        {
          "t": "העניין",
          "s": 4.94,
          "e": 5.82
        }
      ]
    },
    {
      "start": 5.82,
      "end": 9.06,
      "text": "למניה אין קרן וריבית בכלל",
      "words": [
        {
          "t": "למניה",
          "s": 5.82,
          "e": 6.28
        },
        {
          "t": "אין",
          "s": 6.28,
          "e": 6.64
        },
        {
          "t": "קרן",
          "s": 6.64,
          "e": 7.1
        },
        {
          "t": "וריבית",
          "s": 7.1,
          "e": 7.78
        },
        {
          "t": "בכלל",
          "s": 7.78,
          "e": 9.06
        }
      ]
    },
    {
      "start": 9.06,
      "end": 10.12,
      "text": "אין קרן וריבית",
      "words": [
        {
          "t": "אין",
          "s": 9.06,
          "e": 9.22
        },
        {
          "t": "קרן",
          "s": 9.22,
          "e": 9.54
        },
        {
          "t": "וריבית",
          "s": 9.54,
          "e": 10.12
        }
      ]
    },
    {
      "start": 10.12,
      "end": 11.69,
      "text": "אז אין מה לבדוק —",
      "words": [
        {
          "t": "אז",
          "s": 10.12,
          "e": 10.5
        },
        {
          "t": "אין",
          "s": 10.5,
          "e": 10.66
        },
        {
          "t": "מה",
          "s": 10.66,
          "e": 10.78
        },
        {
          "t": "לבדוק",
          "s": 10.78,
          "e": 11.69
        },
        {
          "t": "—",
          "s": 11.69,
          "e": 11.69
        }
      ]
    },
    {
      "start": 11.69,
      "end": 13.4,
      "text": "מבחן ה-SPPI פשוט לא",
      "words": [
        {
          "t": "מבחן",
          "s": 11.69,
          "e": 12.05
        },
        {
          "t": "ה-SPPI",
          "s": 12.05,
          "e": 12.75
        },
        {
          "t": "פשוט",
          "s": 12.75,
          "e": 13.21
        },
        {
          "t": "לא",
          "s": 13.21,
          "e": 13.37
        }
      ]
    },
    {
      "start": 13.4,
      "end": 14.68,
      "text": "רלוונטי",
      "words": [
        {
          "t": "רלוונטי",
          "s": 13.4,
          "e": 14.68
        }
      ]
    },
    {
      "start": 14.68,
      "end": 16.28,
      "text": "לכן מניה נופלת לברירת",
      "words": [
        {
          "t": "לכן",
          "s": 14.68,
          "e": 14.96
        },
        {
          "t": "מניה",
          "s": 14.96,
          "e": 15.28
        },
        {
          "t": "נופלת",
          "s": 15.28,
          "e": 15.82
        },
        {
          "t": "לברירת",
          "s": 15.82,
          "e": 16.28
        }
      ]
    },
    {
      "start": 16.28,
      "end": 17.26,
      "text": "המחדל",
      "words": [
        {
          "t": "המחדל",
          "s": 16.28,
          "e": 17.26
        }
      ]
    },
    {
      "start": 17.26,
      "end": 19.95,
      "text": "שווי הוגן דרך רווח והפסד",
      "words": [
        {
          "t": "שווי",
          "s": 17.26,
          "e": 17.5
        },
        {
          "t": "הוגן",
          "s": 17.5,
          "e": 17.98
        },
        {
          "t": "דרך",
          "s": 17.98,
          "e": 18.44
        },
        {
          "t": "רווח",
          "s": 18.44,
          "e": 18.8
        },
        {
          "t": "והפסד",
          "s": 18.8,
          "e": 19.9
        }
      ]
    },
    {
      "start": 19.95,
      "end": 22.56,
      "text": "כל תנודה בשווי ישר לדוח",
      "words": [
        {
          "t": "כל",
          "s": 19.95,
          "e": 20.09
        },
        {
          "t": "תנודה",
          "s": 20.09,
          "e": 20.43
        },
        {
          "t": "בשווי",
          "s": 20.43,
          "e": 21.01
        },
        {
          "t": "ישר",
          "s": 21.01,
          "e": 21.57
        },
        {
          "t": "לדוח",
          "s": 21.57,
          "e": 22.53
        }
      ]
    },
    {
      "start": 22.56,
      "end": 24.15,
      "text": "אבל יש דלת אחת",
      "words": [
        {
          "t": "אבל",
          "s": 22.56,
          "e": 22.72
        },
        {
          "t": "יש",
          "s": 22.72,
          "e": 22.92
        },
        {
          "t": "דלת",
          "s": 22.92,
          "e": 23.24
        },
        {
          "t": "אחת",
          "s": 23.24,
          "e": 24.15
        }
      ]
    },
    {
      "start": 24.15,
      "end": 25.78,
      "text": "בקנייה אתה רשאי לבחור",
      "words": [
        {
          "t": "בקנייה",
          "s": 24.15,
          "e": 24.89
        },
        {
          "t": "אתה",
          "s": 24.89,
          "e": 25.03
        },
        {
          "t": "רשאי",
          "s": 25.03,
          "e": 25.35
        },
        {
          "t": "לבחור",
          "s": 25.35,
          "e": 25.73
        }
      ]
    },
    {
      "start": 25.78,
      "end": 26.18,
      "text": "להציג",
      "words": [
        {
          "t": "להציג",
          "s": 25.78,
          "e": 26.18
        }
      ]
    },
    {
      "start": 26.18,
      "end": 27.8,
      "text": "את שינויי השווי ב-OCI",
      "words": [
        {
          "t": "את",
          "s": 26.18,
          "e": 26.34
        },
        {
          "t": "שינויי",
          "s": 26.34,
          "e": 26.68
        },
        {
          "t": "השווי",
          "s": 26.68,
          "e": 27.14
        },
        {
          "t": "ב-OCI",
          "s": 27.14,
          "e": 27.8
        }
      ]
    },
    {
      "start": 27.8,
      "end": 29.08,
      "text": "במקום",
      "words": [
        {
          "t": "במקום",
          "s": 27.8,
          "e": 28.88
        }
      ]
    },
    {
      "start": 29.08,
      "end": 30.1,
      "text": "רק שים לב —",
      "words": [
        {
          "t": "רק",
          "s": 29.08,
          "e": 29.44
        },
        {
          "t": "שים",
          "s": 29.44,
          "e": 29.66
        },
        {
          "t": "לב",
          "s": 29.66,
          "e": 30.1
        },
        {
          "t": "—",
          "s": 30.1,
          "e": 30.1
        }
      ]
    },
    {
      "start": 30.1,
      "end": 32.12,
      "text": "הבחירה הזו בלתי-חוזרת",
      "words": [
        {
          "t": "הבחירה",
          "s": 30.1,
          "e": 30.46
        },
        {
          "t": "הזו",
          "s": 30.46,
          "e": 30.66
        },
        {
          "t": "בלתי-חוזרת",
          "s": 30.66,
          "e": 32.02
        }
      ]
    },
    {
      "start": 32.12,
      "end": 33.55,
      "text": "עושים אותה פעם אחת",
      "words": [
        {
          "t": "עושים",
          "s": 32.12,
          "e": 32.36
        },
        {
          "t": "אותה",
          "s": 32.36,
          "e": 32.6
        },
        {
          "t": "פעם",
          "s": 32.6,
          "e": 32.8
        },
        {
          "t": "אחת",
          "s": 32.8,
          "e": 33.24
        }
      ]
    },
    {
      "start": 33.55,
      "end": 35.62,
      "text": "ואי אפשר להתחרט מחר",
      "words": [
        {
          "t": "ואי",
          "s": 33.55,
          "e": 34.06
        },
        {
          "t": "אפשר",
          "s": 34.06,
          "e": 34.33
        },
        {
          "t": "להתחרט",
          "s": 34.33,
          "e": 34.78
        },
        {
          "t": "מחר",
          "s": 34.78,
          "e": 35.62
        }
      ]
    },
    {
      "start": 35.62,
      "end": 37.72,
      "text": "מניה היא FVTPL כברירת",
      "words": [
        {
          "t": "מניה",
          "s": 35.62,
          "e": 35.92
        },
        {
          "t": "היא",
          "s": 35.92,
          "e": 36.18
        },
        {
          "t": "FVTPL",
          "s": 36.18,
          "e": 37.24
        },
        {
          "t": "כברירת",
          "s": 37.24,
          "e": 37.72
        }
      ]
    },
    {
      "start": 37.72,
      "end": 38.71,
      "text": "מחדל",
      "words": [
        {
          "t": "מחדל",
          "s": 37.72,
          "e": 38.71
        }
      ]
    },
    {
      "start": 38.71,
      "end": 40.78,
      "text": "חלופת ה-OCI קיימת —",
      "words": [
        {
          "t": "חלופת",
          "s": 38.71,
          "e": 39.15
        },
        {
          "t": "ה-OCI",
          "s": 39.15,
          "e": 39.69
        },
        {
          "t": "קיימת",
          "s": 39.69,
          "e": 40.75
        },
        {
          "t": "—",
          "s": 40.75,
          "e": 40.75
        }
      ]
    },
    {
      "start": 40.78,
      "end": 42.5,
      "text": "אבל בוחרים אותה פעם אחת",
      "words": [
        {
          "t": "אבל",
          "s": 40.78,
          "e": 40.92
        },
        {
          "t": "בוחרים",
          "s": 40.92,
          "e": 41.34
        },
        {
          "t": "אותה",
          "s": 41.34,
          "e": 41.56
        },
        {
          "t": "פעם",
          "s": 41.56,
          "e": 41.8
        },
        {
          "t": "אחת",
          "s": 41.8,
          "e": 42.5
        }
      ]
    },
    {
      "start": 42.5,
      "end": 43.92,
      "text": "בהתחלה לתמיד",
      "words": [
        {
          "t": "בהתחלה",
          "s": 42.5,
          "e": 43.0
        },
        {
          "t": "לתמיד",
          "s": 43.0,
          "e": 43.92
        }
      ]
    }
  ]
}